ranx/__init__.py
ranx/downloader.py
ranx/io.py
ranx/ranxhub.py
ranx/utils.py
ranx/data_structures/__init__.py
ranx/data_structures/common.py
ranx/data_structures/frozenset_dict.py
ranx/data_structures/generic.py
ranx/data_structures/optimization_report.py
ranx/data_structures/qrels.py
ranx/data_structures/report.py
ranx/data_structures/run.py
ranx/fusion/__init__.py
ranx/fusion/bayesfuse.py
ranx/fusion/bordafuse.py
ranx/fusion/comb_anz.py
ranx/fusion/comb_gmnz.py
ranx/fusion/comb_max.py
ranx/fusion/comb_med.py
ranx/fusion/comb_min.py
ranx/fusion/comb_mnz.py
ranx/fusion/comb_sum.py
ranx/fusion/common.py
ranx/fusion/condorcet.py
ranx/fusion/isr.py
ranx/fusion/log_isr.py
ranx/fusion/logn_isr.py
ranx/fusion/mapfuse.py
ranx/fusion/mixed.py
ranx/fusion/posfuse.py
ranx/fusion/probfuse.py
ranx/fusion/rbc.py
ranx/fusion/rrf.py
ranx/fusion/segfuse.py
ranx/fusion/slidefuse.py
ranx/fusion/weighted_bordafuse.py
ranx/fusion/weighted_condorcet.py
ranx/fusion/wmnz.py
ranx/fusion/wsum.py
ranx/fusion_optimization/__init__.py
ranx/fusion_optimization/optimize_bayesfuse.py
ranx/fusion_optimization/optimize_comb_gmnz.py
ranx/fusion_optimization/optimize_logn_isr.py
ranx/fusion_optimization/optimize_mapfuse.py
ranx/fusion_optimization/optimize_mixed.py
ranx/fusion_optimization/optimize_posfuse.py
ranx/fusion_optimization/optimize_probfuse.py
ranx/fusion_optimization/optimize_rbc.py
ranx/fusion_optimization/optimize_rrf.py
ranx/fusion_optimization/optimize_segfuse.py
ranx/fusion_optimization/optimize_slidefuse.py
ranx/fusion_optimization/optimize_weighted_bordafuse.py
ranx/fusion_optimization/optimize_weighted_condorcet.py
ranx/fusion_optimization/optimize_weights.py
ranx/fusion_optimization/optimize_wmnz.py
ranx/fusion_optimization/optimize_wsum.py
ranx/meta/__init__.py
ranx/meta/compare.py
ranx/meta/evaluate.py
ranx/meta/fuse.py
ranx/meta/normalize.py
ranx/meta/optimize_fusion.py
ranx/meta/plot.py
ranx/metrics/__init__.py
ranx/metrics/average_precision.py
ranx/metrics/bpref.py
ranx-0.3.21.dist-info/LICENSE
ranx-0.3.21.dist-info/METADATA
ranx-0.3.21.dist-info/WHEEL
ranx-0.3.21.dist-info/top_level.txt
ranx-0.3.21.dist-info/RECORD
