Metadata-Version: 2.1
Name: ranx
Version: 0.3.21
Summary: ranx: A Blazing-Fast Python Library for Ranking Evaluation, Comparison, and Fusion
Home-page: https://github.com/AmenRa/ranx
Author: Elias Bassani
Author-email: elias.bssn@gmail.com
Keywords: trec_eval,information retrieval,recommender systems,evaluation,ranking,fusion,metasearch,numba
Classifier: Programming Language :: Python :: 3
Classifier: License :: OSI Approved :: MIT License
Classifier: Intended Audience :: Science/Research
Classifier: Operating System :: OS Independent
Classifier: Topic :: Text Processing :: General
Requires-Python: >=3.8
License-File: LICENSE
Requires-Dist: numpy
Requires-Dist: numba>=0.54.1
Requires-Dist: pandas
Requires-Dist: tabulate
Requires-Dist: tqdm
Requires-Dist: scipy>=1.8.0
Requires-Dist: ir-datasets
Requires-Dist: rich
Requires-Dist: orjson
Requires-Dist: lz4
Requires-Dist: cbor2
Requires-Dist: seaborn
Requires-Dist: fastparquet
